[
   
          {
            "id":1,
            "title":"1.您的年龄：",
            "list":["小于25岁","26-35岁","36-45岁","46-55岁","56岁以上"]
          },
    
    
         {
            "id":2,
            "title":"2、您的性别：",
            "list":["美女","帅哥"]
          },
    
        {
            "id":3,
            "title":"3.您的英语水平：",
            "list":["工作、生活可正常与英美语系老外交流","可看懂工作邮件，口语欠缺","可进行简单对话","毕业后完全没有用过","零基础"]
        },
    
        {
            "id":4,
            "title":"4、您觉得英语最大的难点在于：",
            "list":["没时间","时间不固定无法跟上英语培训的课程","没有英语语境","难以坚持"]
        },
    
        {
            "id":5,
            "title":"5、您愿意接受VIPABC客服人员电话回访，预约免费试听课程吗？",
            "list":["我愿意","我不愿意"]
        }
]
